<?xml version="1.0" encoding="UTF-8" standalone="no"?>
<window xmlns="http://schemas.haulmont.com/cuba/screen/window.xsd"
        caption="Facadelayer editieren"
        focusComponent="form"
        messagesPack="ch.so.agi.simi.web.screens.facadelayer">
    <data>
        <instance id="facadeLayerDc"
                  class="ch.so.agi.simi.entity.FacadeLayer"
                  view="fl-list-of-ds">
            <loader/>
            <collection id="dataSetListPropertiesDc" property="dataSetListProperties"/>
        </instance>
    </data>
    <dialogMode height="600"
                width="800"/>
    <layout expand="editActions" spacing="true">
        <form id="form" dataContainer="facadeLayerDc">
            <column width="250px">
                <textField id="identifierField" property="identifier" caption="Identifier"/>
                <textField id="titleField" property="title" caption="Titel"/>
                <checkBox id="inWGCField" property="inWGC" caption="In WGC publiziert?"/>
                <textArea id="remarksField" property="remarks" rows="5" caption="Bemerkungen intern"/>
            </column>
        </form>
        <groupBox id="dataSetListPropertiesBox" caption="Liste der DataSets">
            <table id="dataSetListPropertiesTable" dataContainer="dataSetListPropertiesDc" width="100%" height="200px"
                   editable="true">
                <actions>
                    <action id="create" type="create"/>
                    <action id="edit" type="edit"/>
                    <action id="remove" type="remove"/>
                </actions>
                <columns>
                    <column id="dataset" caption="Dataset" width="600"/>
                    <column id="sort" editable="true" width="50" caption="Sort."/>
                    <column id="visible" editable="true" caption="Sicht." width="50" sortable="false"/>
                    <column id="transparency" caption="Trans. [%]" editable="true" sortable="false"/>
                </columns>
                <buttonsPanel>
                    <button action="dataSetListPropertiesTable.create" caption="Listeneintrag erstellen" stylename="primary"/>
                    <button action="dataSetListPropertiesTable.edit" caption="Listeneintrag editieren" stylename="primary"/>
                    <button action="dataSetListPropertiesTable.remove" caption="Listeneintrag löschen" stylename="danger"/>
                </buttonsPanel>
            </table>
        </groupBox>
        <hbox id="editActions" spacing="true">
            <button action="windowCommitAndClose" caption="Speichern und schliessen" stylename="primary"/>
            <button action="windowClose" caption="Schliessen ohne zu speichern" stylename="danger"/>
        </hbox>
    </layout>
</window>
